{
	"downloadUrl": "https://git.door43.org/unfoldingWord/en_ult",
	"publisher": "unfoldingWord",
	"publisherUrl": "https://unfoldingword.org",
	"title": "unfoldingWord® Literal Text",
	"license": "CC BY-SA 4.0",
	"authors": [
		"Nicholas Alsop",
		"Scott Bayer",
		"Larry T Brooks, M.Div., Assemblies of God Theological Seminary",
		"Matt Carlton",
		"George \"Drew\" Curley, M.Div., PhD, Professor of Biblical Languages",
		"Dan Dennison",
		"Jamie Duguid",
		"Paul M Fahnestock, M.Div. Reformed Theological Seminary, D.Min. Pittsburgh Theological Seminary",
		"Michael Francis",
		"Laura Glassel, MA in Bible Translation",
		"Jesse Griffin, BA Biblical Studies, MA Biblical Languages",
		"Jesse Harris",
		"C. Harry Harriss, M.Div.",
		"Alrick G. Headley, M.Div., Th.M.",
		"Bram van den Heuvel, M.A.",
		"John Huffman",
		"D. Allen Hutchison, MA in Old Testament, MA in New Testament",
		"Jack Messarra",
		"Gene Mullen",
		"Adam W. Nagelvoort, M.Div. Academic Ministries, Columbia International University",
		"Timothy Neu, Ph.D. Biblical Studies",
		"Kristy Nickell",
		"Tom Nickell",
		"Elizabeth Oakes, BA in Religious Studies, Linguistics",
		"Perry Oakes, PhD in Old Testament, MA in Linguistics",
		"James N. Pohlig, M.Div., MA in Linguistics, D. Litt. in Biblical Languages",
		"Ward Pyles, M.Div., Western Baptist Theological Seminary",
		"Susan Quigley, MA in Linguistics",
		"Dean Ropp",
		"Joel D. Ruark, M.A.Th., Th.M., Ph.D. in Old Testament, University of Stellenbosch",
		"Larry Sallee, Th.M Dallas Theological Seminary, D.Min. Columbia Biblical Seminary",
		"Peter Smircich, BA Philosophy",
		"Doug Smith, M.T.S., M.Div., Th.M., Midwestern Baptist Theological Seminary",
		"Leonard Smith",
		"Suzanna Smith",
		"Tim Span",
		"Dave Statezni, BA Orig langs., M.Div. Fuller Theological Seminary",
		"Maria Tijerina",
		"David Trombold, M. Div.",
		"Aaron Valdizan, M.Div., Th.M. in Old Testament, The Masters Seminary",
		"James Vigen",
		"Hendrik \"Henry\" de Vries",
		"Thomas Warren, M.Div., Trinity Evangelical Divinity School, D.Min, Reformed Theological Seminary",
		"Angela Westmoreland, M.A. in Theological Studies (Biblical Language track)",
		"Henry Whitney, BA Linguistics",
		"Benjamin Wright, MA Applied Linguistics, Dallas International University",
		"Grant Ailie, BA Biblical Studies, M.Div.",
		"Door43 World Missions Community"
	],
	"about": "frt"
}
